bbox_annotation_tools-1.0.2.dist-info/licenses/LICENSE
bbox_tools/__init__.py
bbox_tools/bbox_gui_editor.py
bbox_tools/config.py
bbox_tools/drug_code_viewer.py
bbox_annotation_tools-1.0.2.dist-info/METADATA
bbox_annotation_tools-1.0.2.dist-info/WHEEL
bbox_annotation_tools-1.0.2.dist-info/entry_points.txt
bbox_annotation_tools-1.0.2.dist-info/top_level.txt
bbox_annotation_tools-1.0.2.dist-info/RECORD
