Metadata-Version: 2.4
Name: bbox-annotation-tools
Version: 1.0.2
Summary: Bounding Box Annotation Editing and Analysis Tools
Home-page: https://github.com/LEEYH205/bbox-annotation-tools
Author: LEEYH205
Author-email: LEEYH205 <ejrdkachry@gmail.com>
Maintainer-email: LEEYH205 <ejrdkachry@gmail.com>
License: MIT
Project-URL: Homepage, https://github.com/LEEYH205/bbox-annotation-tools
Project-URL: Repository, https://github.com/LEEYH205/bbox-annotation-tools
Project-URL: Bug Tracker, https://github.com/LEEYH205/bbox-annotation-tools/issues
Keywords: bbox,annotation,computer-vision,image-processing,drug-detection
Classifier: Development Status :: 4 - Beta
Classifier: Intended Audience :: Developers
Classifier: Intended Audience :: Science/Research
Classifier: License :: OSI Approved :: MIT License
Classifier: Operating System :: OS Independent
Classifier: Programming Language :: Python :: 3
Classifier: Programming Language :: Python :: 3.7
Classifier: Programming Language :: Python :: 3.8
Classifier: Programming Language :: Python :: 3.9
Classifier: Programming Language :: Python :: 3.10
Classifier: Programming Language :: Python :: 3.11
Classifier: Topic :: Scientific/Engineering :: Artificial Intelligence
Classifier: Topic :: Scientific/Engineering :: Image Processing
Requires-Python: >=3.7
License-File: LICENSE
Requires-Dist: opencv-python>=4.5.0
Requires-Dist: numpy>=1.19.0
Requires-Dist: matplotlib>=3.3.0
Requires-Dist: Pillow>=8.0.0
Dynamic: author
Dynamic: home-page
Dynamic: license-file
Dynamic: requires-python
